[{"Position":1,"DriverNumber":"16","BroadcastName":"C LECLERC","TeamName":"Ferrari","Time":"01:31.632","Status":"","Points":0},{"Position":10,"DriverNumber":"81","BroadcastName":"O PIASTRI","TeamName":"McLaren","Time":"01:32.310","Status":"","Points":0},{"Position":11,"DriverNumber":"20","BroadcastName":"K MAGNUSSEN","TeamName":"Haas F1 Team","Time":"01:32.338","Status":"","Points":0},{"Position":12,"DriverNumber":"27","BroadcastName":"N HULKENBERG","TeamName":"Haas F1 Team","Time":"01:32.366","Status":"","Points":0},{"Position":13,"DriverNumber":"14","BroadcastName":"F ALONSO","TeamName":"Aston Martin","Time":"01:32.387","Status":"","Points":0},{"Position":14,"DriverNumber":"77","BroadcastName":"V BOTTAS","TeamName":"Kick Sauber","Time":"01:32.706","Status":"","Points":0},{"Position":15,"DriverNumber":"2","BroadcastName":"L SARGEANT","TeamName":"Williams","Time":"01:33.026","Status":"","Points":0},{"Position":16,"DriverNumber":"3","BroadcastName":"D RICCIARDO","TeamName":"RB","Time":"01:33.323","Status":"","Points":0},{"Position":17,"DriverNumber":"31","BroadcastName":"E OCON","TeamName":"Alpine","Time":"01:33.481","Status":"","Points":0},{"Position":18,"DriverNumber":"22","BroadcastName":"Y TSUNODA","TeamName":"RB","Time":"01:33.523","Status":"","Points":0},{"Position":19,"DriverNumber":"18","BroadcastName":"L STROLL","TeamName":"Aston Martin","Time":"01:35.560","Status":"","Points":0},{"Position":2,"DriverNumber":"44","BroadcastName":"L HAMILTON","TeamName":"Mercedes","Time":"01:31.746","Status":"","Points":0},{"Position":20,"DriverNumber":"10","BroadcastName":"P GASLY","TeamName":"Alpine","Time":"","Status":"","Points":0},{"Position":3,"DriverNumber":"1","BroadcastName":"M VERSTAPPEN","TeamName":"Red Bull Racing","Time":"01:31.773","Status":"","Points":0},{"Position":4,"DriverNumber":"4","BroadcastName":"L NORRIS","TeamName":"McLaren","Time":"01:31.944","Status":"","Points":0},{"Position":5,"DriverNumber":"38","BroadcastName":"O BEARMAN","TeamName":"Ferrari","Time":"01:32.186","Status":"","Points":0},{"Position":6,"DriverNumber":"24","BroadcastName":"G ZHOU","TeamName":"Kick Sauber","Time":"01:32.208","Status":"","Points":0},{"Position":7,"DriverNumber":"63","BroadcastName":"G RUSSELL","TeamName":"Mercedes","Time":"01:32.254","Status":"","Points":0},{"Position":8,"DriverNumber":"11","BroadcastName":"S PEREZ","TeamName":"Red Bull Racing","Time":"01:32.273","Status":"","Points":0},{"Position":9,"DriverNumber":"23","BroadcastName":"A ALBON","TeamName":"Williams","Time":"01:32.307","Status":"","Points":0}]